syrup/__init__.py
syrup/api/__init__.py
syrup/api/errors/__init__.py
syrup/api/errors/http_error.py
syrup/api/httpx/__init__.py
syrup/api/httpx/response.py
syrup/lib/__init__.py
syrup/lib/store/__init__.py
syrup/lib/store/cache/__init__.py
syrup/lib/store/redis/__init__.py
syrup/lib/store/redis/client.py
syrup/lib/store/redis/types.py
syrup/lib/store/redis/tests/__init__.py
syrup/lib/store/redis/tests/test_client.py
syrup/lib/store/tortoise/__init__.py
syrup/lib/store/tortoise/cache.py
syrup/lib/store/tortoise/converters.py
syrup/lib/store/tortoise/exceptions.py
syrup/lib/store/tortoise/expressions.py
syrup/lib/store/tortoise/filters.py
syrup/lib/store/tortoise/functions.py
syrup/lib/store/tortoise/indexes.py
syrup/lib/store/tortoise/json_coder.py
syrup/lib/store/tortoise/manager.py
syrup/lib/store/tortoise/models.py
syrup/lib/store/tortoise/query_utils.py
syrup/lib/store/tortoise/queryset.py
syrup/lib/store/tortoise/router.py
syrup/lib/store/tortoise/signals.py
syrup/lib/store/tortoise/timezone.py
syrup/lib/store/tortoise/transactions.py
syrup/lib/store/tortoise/utils.py
syrup/lib/store/tortoise/validators.py
syrup/lib/store/tortoise/backends/__init__.py
syrup/lib/store/tortoise/backends/asyncpg/__init__.py
syrup/lib/store/tortoise/backends/asyncpg/client.py
syrup/lib/store/tortoise/backends/asyncpg/executor.py
syrup/lib/store/tortoise/backends/asyncpg/schema_generator.py
syrup/lib/store/tortoise/backends/base/__init__.py
syrup/lib/store/tortoise/backends/base/client.py
syrup/lib/store/tortoise/backends/base/config_generator.py
syrup/lib/store/tortoise/backends/base/executor.py
syrup/lib/store/tortoise/backends/base/schema_generator.py
syrup/lib/store/tortoise/backends/mysql/__init__.py
syrup/lib/store/tortoise/backends/mysql/client.py
syrup/lib/store/tortoise/backends/mysql/executor.py
syrup/lib/store/tortoise/backends/mysql/schema_generator.py
syrup/lib/store/tortoise/backends/sqlite/__init__.py
syrup/lib/store/tortoise/backends/sqlite/client.py
syrup-0.0.2.dist-info/LICENSE
syrup-0.0.2.dist-info/METADATA
syrup-0.0.2.dist-info/WHEEL
syrup-0.0.2.dist-info/top_level.txt
syrup-0.0.2.dist-info/RECORD
